LICENSE
MANIFEST.in
README.text
setup.py
bin/rapydscript
rapydscript/__init__.py
rapydscript/__init__.pyc
rapydscript/codecheck.py
rapydscript/compiler.py
rapydscript/exceptions.py
rapydscript/grammar.ometa
rapydscript/grammar.py
rapydscript/grammar.pyc
rapydscript/stdlib.js
rapydscript/stdlib.pyj
rapydscript/stdlib2.js
rapydscript/stdlib2.pyj
rapydscript/translator.ometa
rapydscript/unittest.pyj
rapydscript/yql.pyj
rapydscript.egg-info/PKG-INFO
rapydscript.egg-info/SOURCES.txt
rapydscript.egg-info/dependency_links.txt
rapydscript.egg-info/requires.txt
rapydscript.egg-info/top_level.txt
tests/__init__.py
tests/__init__.pyc
tests/grammartests.py
tests/grammartests.pyc
tests/integrationtests.py
tests/integrationtests.pyc
tests/testdata/builtin.js.ref
tests/testdata/builtin.pyj
tests/testdata/classes.js.ref
tests/testdata/classes.pyj
tests/testdata/comparisons.js.ref
tests/testdata/comparisons.pyj
tests/testdata/dowhile.js.ref
tests/testdata/dowhile.pyj
tests/testdata/except.js.ref
tests/testdata/except.pyj
tests/testdata/functions.js.ref
tests/testdata/functions.pyj
tests/testdata/mapfilter.js.ref
tests/testdata/mapfilter.pyj
tests/testdata/regexstr.js.ref
tests/testdata/regexstr.pyj