Metadata-Version: 1.0
Name: rapydscript
Version: 0.0.2
Summary: Pythonic JavaScript syntax with support for advanced Python functionality
Home-page: http://rapydscript.pyjeon.com
Author: Alexander Tsepkov
Author-email: UNKNOWN
License: GNU GPL3
Platform: any
